{"paging": {"pageIndex": 1, "pageSize": 100, "total": 43}, "baseComponent": {"id": "AYf8XZoOWrasIp79rAgz", "key": "fga-eps-mds_2023-1-PUMA-ProjectService", "name": "2023-1-PUMA-ProjectService", "qualifier": "TRK", "measures": [{"metric": "duplicated_lines_density", "value": "0.0", "bestValue": true}, {"metric": "functions", "value": "356"}, {"metric": "security_rating", "value": "1.0", "bestValue": true}, {"metric": "files", "value": "22"}, {"metric": "complexity", "value": "393"}, {"metric": "ncloc", "value": "1842"}, {"metric": "coverage", "value": "70.8", "bestValue": false}, {"metric": "comment_lines_density", "value": "2.3", "bestValue": false}]}, "components": [{"id": "AYhUIFXjntWG4CW0Dqk5", "key": "fga-eps-mds_2023-1-PUMA-ProjectService:src/service/AlocateService.js", "name": "AlocateService.js", "qualifier": "FIL", "path": "src/service/AlocateService.js", "language": "js", "measures": [{"metric": "complexity", "value": "0"}, {"metric": "functions", "value": "0"}, {"metric": "ncloc", "value": "0"}, {"metric": "security_rating", "value": "1.0", "bestValue": true}, {"metric": "comment_lines_density", "value": "100.0", "bestValue": true}, {"metric": "files", "value": "1"}, {"metric": "duplicated_lines_density", "value": "0.0", "bestValue": true}, {"metric": "test_errors", "value": "0", "bestValue": true}, {"metric": "test_failures", "value": "0", "bestValue": true}]}, {"id": "AYhUIFXjntWG4CW0Dqk9", "key": "fga-eps-mds_2023-1-PUMA-ProjectService:src/controller/ClassController.js", "name": "ClassController.js", "qualifier": "FIL", "path": "src/controller/ClassController.js", "language": "js", "measures": [{"metric": "complexity", "value": "8"}, {"metric": "functions", "value": "8"}, {"metric": "ncloc", "value": "45"}, {"metric": "coverage", "value": "100.0", "bestValue": true}, {"metric": "security_rating", "value": "1.0", "bestValue": true}, {"metric": "comment_lines_density", "value": "0.0", "bestValue": false}, {"metric": "files", "value": "1"}, {"metric": "duplicated_lines_density", "value": "0.0", "bestValue": true}, {"metric": "test_errors", "value": "0", "bestValue": true}, {"metric": "test_failures", "value": "0", "bestValue": true}]}, {"id": "AYhUIFXjntWG4CW0DqlR", "key": "fga-eps-mds_2023-1-PUMA-ProjectService:tests/unit/controller/ClassController.test.js", "name": "ClassController.test.js", "qualifier": "UTS", "path": "tests/unit/controller/ClassController.test.js", "language": "js", "measures": [{"metric": "security_rating", "value": "1.0", "bestValue": true}, {"metric": "duplicated_lines_density", "value": "0.0", "bestValue": true}, {"metric": "test_errors", "value": "0", "bestValue": true}, {"metric": "test_failures", "value": "0", "bestValue": true}]}, {"id": "AYhUIFXjntWG4CW0Dqka", "key": "fga-eps-mds_2023-1-PUMA-ProjectService:src/repository/ClassRepository.js", "name": "ClassRepository.js", "qualifier": "FIL", "path": "src/repository/ClassRepository.js", "language": "js", "measures": [{"metric": "functions", "value": "34"}, {"metric": "security_rating", "value": "1.0", "bestValue": true}, {"metric": "files", "value": "1"}, {"metric": "complexity", "value": "39"}, {"metric": "ncloc", "value": "139"}, {"metric": "coverage", "value": "73.1", "bestValue": false}, {"metric": "comment_lines_density", "value": "0.0", "bestValue": false}, {"metric": "duplicated_lines_density", "value": "0.0", "bestValue": true}, {"metric": "test_errors", "value": "0", "bestValue": true}, {"metric": "test_failures", "value": "0", "bestValue": true}]}, {"id": "AYhUIFXjntWG4CW0DqlJ", "key": "fga-eps-mds_2023-1-PUMA-ProjectService:tests/unit/repository/ClassRepository.test.js", "name": "ClassRepository.test.js", "qualifier": "UTS", "path": "tests/unit/repository/ClassRepository.test.js", "language": "js", "measures": [{"metric": "security_rating", "value": "1.0", "bestValue": true}, {"metric": "duplicated_lines_density", "value": "0.0", "bestValue": true}, {"metric": "test_errors", "value": "0", "bestValue": true}, {"metric": "test_failures", "value": "0", "bestValue": true}]}, {"id": "AYhUIFXjntWG4CW0Dqk_", "key": "fga-eps-mds_2023-1-PUMA-ProjectService:src/controller", "name": "controller", "qualifier": "DIR", "path": "src/controller", "measures": [{"metric": "duplicated_lines_density", "value": "0.0", "bestValue": true}, {"metric": "functions", "value": "102"}, {"metric": "security_rating", "value": "1.0", "bestValue": true}, {"metric": "files", "value": "6"}, {"metric": "complexity", "value": "109"}, {"metric": "ncloc", "value": "484"}, {"metric": "coverage", "value": "77.8", "bestValue": false}, {"metric": "comment_lines_density", "value": "0.0", "bestValue": false}]}, {"id": "AYhUIFXjntWG4CW0DqlS", "key": "fga-eps-mds_2023-1-PUMA-ProjectService:tests/unit/controller", "name": "controller", "qualifier": "DIR", "path": "tests/unit/controller", "measures": [{"metric": "security_rating", "value": "1.0", "bestValue": true}]}, {"id": "AYhUIFXkntWG4CW0DqlW", "key": "fga-eps-mds_2023-1-PUMA-ProjectService:dbconfig", "name": "dbconfig", "qualifier": "DIR", "path": "dbconfig", "measures": [{"metric": "duplicated_lines_density", "value": "0.0", "bestValue": true}, {"metric": "functions", "value": "3"}, {"metric": "security_rating", "value": "1.0", "bestValue": true}, {"metric": "files", "value": "2"}, {"metric": "complexity", "value": "8"}, {"metric": "ncloc", "value": "289"}, {"metric": "coverage", "value": "35.9", "bestValue": false}, {"metric": "comment_lines_density", "value": "1.0", "bestValue": false}]}, {"id": "AYhUIFXjntWG4CW0DqlU", "key": "fga-eps-mds_2023-1-PUMA-ProjectService:dbconfig/dbConfig.js", "name": "dbConfig.js", "qualifier": "FIL", "path": "dbconfig/dbConfig.js", "language": "js", "measures": [{"metric": "complexity", "value": "8"}, {"metric": "functions", "value": "3"}, {"metric": "ncloc", "value": "47"}, {"metric": "coverage", "value": "34.2", "bestValue": false}, {"metric": "security_rating", "value": "1.0", "bestValue": true}, {"metric": "comment_lines_density", "value": "6.0", "bestValue": false}, {"metric": "files", "value": "1"}, {"metric": "duplicated_lines_density", "value": "0.0", "bestValue": true}, {"metric": "test_errors", "value": "0", "bestValue": true}, {"metric": "test_failures", "value": "0", "bestValue": true}]}, {"id": "AYhUIFXkntWG4CW0DqlV", "key": "fga-eps-mds_2023-1-PUMA-ProjectService:dbconfig/dbSchema.js", "name": "dbSchema.js", "qualifier": "FIL", "path": "dbconfig/dbSchema.js", "language": "js", "measures": [{"metric": "complexity", "value": "0"}, {"metric": "functions", "value": "0"}, {"metric": "ncloc", "value": "242"}, {"metric": "coverage", "value": "100.0", "bestValue": true}, {"metric": "security_rating", "value": "1.0", "bestValue": true}, {"metric": "comment_lines_density", "value": "0.0", "bestValue": false}, {"metric": "files", "value": "1"}, {"metric": "duplicated_lines_density", "value": "0.0", "bestValue": true}, {"metric": "test_errors", "value": "0", "bestValue": true}, {"metric": "test_failures", "value": "0", "bestValue": true}]}, {"id": "AYhUIFXjntWG4CW0Dqk3", "key": "fga-eps-mds_2023-1-PUMA-ProjectService:src/utils/functions.js", "name": "functions.js", "qualifier": "FIL", "path": "src/utils/functions.js", "language": "js", "measures": [{"metric": "complexity", "value": "3"}, {"metric": "functions", "value": "1"}, {"metric": "ncloc", "value": "5"}, {"metric": "coverage", "value": "0.0", "bestValue": false}, {"metric": "security_rating", "value": "1.0", "bestValue": true}, {"metric": "comment_lines_density", "value": "79.2", "bestValue": false}, {"metric": "files", "value": "1"}, {"metric": "duplicated_lines_density", "value": "0.0", "bestValue": true}, {"metric": "test_errors", "value": "0", "bestValue": true}, {"metric": "test_failures", "value": "0", "bestValue": true}]}, {"id": "AYhUIFXjntWG4CW0Dqk8", "key": "fga-eps-mds_2023-1-PUMA-ProjectService:src/controller/KeywordController.js", "name": "KeywordController.js", "qualifier": "FIL", "path": "src/controller/KeywordController.js", "language": "js", "measures": [{"metric": "complexity", "value": "17"}, {"metric": "functions", "value": "17"}, {"metric": "ncloc", "value": "83"}, {"metric": "coverage", "value": "83.7", "bestValue": false}, {"metric": "security_rating", "value": "1.0", "bestValue": true}, {"metric": "comment_lines_density", "value": "0.0", "bestValue": false}, {"metric": "files", "value": "1"}, {"metric": "duplicated_lines_density", "value": "0.0", "bestValue": true}, {"metric": "test_errors", "value": "0", "bestValue": true}, {"metric": "test_failures", "value": "0", "bestValue": true}]}, {"id": "AYhUIFXjntWG4CW0DqlP", "key": "fga-eps-mds_2023-1-PUMA-ProjectService:tests/unit/controller/KeywordController.test.js", "name": "KeywordController.test.js", "qualifier": "UTS", "path": "tests/unit/controller/KeywordController.test.js", "language": "js", "measures": [{"metric": "security_rating", "value": "1.0", "bestValue": true}, {"metric": "duplicated_lines_density", "value": "0.0", "bestValue": true}, {"metric": "test_errors", "value": "0", "bestValue": true}, {"metric": "test_failures", "value": "0", "bestValue": true}]}, {"id": "AYhUIFXjntWG4CW0DqkZ", "key": "fga-eps-mds_2023-1-PUMA-ProjectService:src/repository/keywordRepository.js", "name": "keywordRepository.js", "qualifier": "FIL", "path": "src/repository/keywordRepository.js", "language": "js", "measures": [{"metric": "complexity", "value": "64"}, {"metric": "functions", "value": "64"}, {"metric": "ncloc", "value": "192"}, {"metric": "coverage", "value": "96.4", "bestValue": false}, {"metric": "security_rating", "value": "1.0", "bestValue": true}, {"metric": "comment_lines_density", "value": "0.0", "bestValue": false}, {"metric": "files", "value": "1"}, {"metric": "duplicated_lines_density", "value": "0.0", "bestValue": true}, {"metric": "test_errors", "value": "0", "bestValue": true}, {"metric": "test_failures", "value": "0", "bestValue": true}]}, {"id": "AYhUIFXjntWG4CW0DqlK", "key": "fga-eps-mds_2023-1-PUMA-ProjectService:tests/unit/repository/KeywordRepository.test.js", "name": "KeywordRepository.test.js", "qualifier": "UTS", "path": "tests/unit/repository/KeywordRepository.test.js", "language": "js", "measures": [{"metric": "security_rating", "value": "1.0", "bestValue": true}, {"metric": "duplicated_lines_density", "value": "0.0", "bestValue": true}, {"metric": "test_errors", "value": "0", "bestValue": true}, {"metric": "test_failures", "value": "0", "bestValue": true}]}, {"id": "AYhUIFXjntWG4CW0DqkY", "key": "fga-eps-mds_2023-1-PUMA-ProjectService:src/repository/knowledgeArea.js", "name": "knowledgeArea.js", "qualifier": "FIL", "path": "src/repository/knowledgeArea.js", "language": "js", "measures": [{"metric": "complexity", "value": "8"}, {"metric": "functions", "value": "8"}, {"metric": "ncloc", "value": "17"}, {"metric": "coverage", "value": "91.7", "bestValue": false}, {"metric": "security_rating", "value": "1.0", "bestValue": true}, {"metric": "comment_lines_density", "value": "0.0", "bestValue": false}, {"metric": "files", "value": "1"}, {"metric": "duplicated_lines_density", "value": "0.0", "bestValue": true}, {"metric": "test_errors", "value": "0", "bestValue": true}, {"metric": "test_failures", "value": "0", "bestValue": true}]}, {"id": "AYhUIFXjntWG4CW0DqlF", "key": "fga-eps-mds_2023-1-PUMA-ProjectService:tests/unit/repository/KnowledgeAreaRepository.test.js", "name": "KnowledgeAreaRepository.test.js", "qualifier": "UTS", "path": "tests/unit/repository/KnowledgeAreaRepository.test.js", "language": "js", "measures": [{"metric": "security_rating", "value": "1.0", "bestValue": true}, {"metric": "duplicated_lines_density", "value": "0.0", "bestValue": true}, {"metric": "test_errors", "value": "0", "bestValue": true}, {"metric": "test_failures", "value": "0", "bestValue": true}]}, {"id": "AYi89DOdSkh8Mld0ki-S", "key": "fga-eps-mds_2023-1-PUMA-ProjectService:src/controller/PartnerProjectController.js", "name": "PartnerProjectController.js", "qualifier": "FIL", "path": "src/controller/PartnerProjectController.js", "language": "js", "measures": [{"metric": "complexity", "value": "17"}, {"metric": "functions", "value": "17"}, {"metric": "ncloc", "value": "52"}, {"metric": "coverage", "value": "0.0", "bestValue": false}, {"metric": "security_rating", "value": "1.0", "bestValue": true}, {"metric": "comment_lines_density", "value": "0.0", "bestValue": false}, {"metric": "files", "value": "1"}, {"metric": "duplicated_lines_density", "value": "0.0", "bestValue": true}, {"metric": "test_errors", "value": "0", "bestValue": true}, {"metric": "test_failures", "value": "0", "bestValue": true}]}, {"id": "AYi89DOdSkh8Mld0ki-R", "key": "fga-eps-mds_2023-1-PUMA-ProjectService:src/repository/partnerProjectRepository.js", "name": "partnerProjectRepository.js", "qualifier": "FIL", "path": "src/repository/partnerProjectRepository.js", "language": "js", "measures": [{"metric": "complexity", "value": "20"}, {"metric": "functions", "value": "20"}, {"metric": "ncloc", "value": "69"}, {"metric": "coverage", "value": "0.0", "bestValue": false}, {"metric": "security_rating", "value": "1.0", "bestValue": true}, {"metric": "comment_lines_density", "value": "0.0", "bestValue": false}, {"metric": "files", "value": "1"}, {"metric": "duplicated_lines_density", "value": "0.0", "bestValue": true}, {"metric": "test_errors", "value": "0", "bestValue": true}, {"metric": "test_failures", "value": "0", "bestValue": true}]}, {"id": "AYhjjaD1HdRBtAUiJyEe", "key": "fga-eps-mds_2023-1-PUMA-ProjectService:src/utils/populaPumaInfo.js", "name": "populaPumaInfo.js", "qualifier": "FIL", "path": "src/utils/populaPumaInfo.js", "language": "js", "measures": [{"metric": "complexity", "value": "0"}, {"metric": "functions", "value": "0"}, {"metric": "ncloc", "value": "38"}, {"metric": "coverage", "value": "100.0", "bestValue": true}, {"metric": "security_rating", "value": "1.0", "bestValue": true}, {"metric": "comment_lines_density", "value": "0.0", "bestValue": false}, {"metric": "files", "value": "1"}, {"metric": "duplicated_lines_density", "value": "0.0", "bestValue": true}, {"metric": "test_errors", "value": "0", "bestValue": true}, {"metric": "test_failures", "value": "0", "bestValue": true}]}, {"id": "AYhjjaD1HdRBtAUiJyEf", "key": "fga-eps-mds_2023-1-PUMA-ProjectService:src/utils/populatePumaInfo.sql", "name": "populatePumaInfo.sql", "qualifier": "FIL", "path": "src/utils/populatePumaInfo.sql", "language": "plsql", "measures": [{"metric": "complexity", "value": "0"}, {"metric": "functions", "value": "0"}, {"metric": "ncloc", "value": "20"}, {"metric": "security_rating", "value": "1.0", "bestValue": true}, {"metric": "comment_lines_density", "value": "0.0", "bestValue": false}, {"metric": "files", "value": "1"}, {"metric": "duplicated_lines_density", "value": "0.0", "bestValue": true}, {"metric": "test_errors", "value": "0", "bestValue": true}, {"metric": "test_failures", "value": "0", "bestValue": true}]}, {"id": "AYhUIFXjntWG4CW0DqkW", "key": "fga-eps-mds_2023-1-PUMA-ProjectService:src/repository/professorRepository.js", "name": "professorRepository.js", "qualifier": "FIL", "path": "src/repository/professorRepository.js", "language": "js", "measures": [{"metric": "complexity", "value": "16"}, {"metric": "functions", "value": "16"}, {"metric": "ncloc", "value": "53"}, {"metric": "coverage", "value": "83.3", "bestValue": false}, {"metric": "security_rating", "value": "1.0", "bestValue": true}, {"metric": "comment_lines_density", "value": "0.0", "bestValue": false}, {"metric": "files", "value": "1"}, {"metric": "duplicated_lines_density", "value": "0.0", "bestValue": true}, {"metric": "test_errors", "value": "0", "bestValue": true}, {"metric": "test_failures", "value": "0", "bestValue": true}]}, {"id": "AYhUIFXjntWG4CW0DqlM", "key": "fga-eps-mds_2023-1-PUMA-ProjectService:tests/unit/repository/ProfessorRepository.test.js", "name": "ProfessorRepository.test.js", "qualifier": "UTS", "path": "tests/unit/repository/ProfessorRepository.test.js", "language": "js", "measures": [{"metric": "security_rating", "value": "1.0", "bestValue": true}, {"metric": "duplicated_lines_density", "value": "0.0", "bestValue": true}, {"metric": "test_errors", "value": "0", "bestValue": true}, {"metric": "test_failures", "value": "0", "bestValue": true}]}, {"id": "AYhUIFXjntWG4CW0Dqk7", "key": "fga-eps-mds_2023-1-PUMA-ProjectService:src/controller/ProjectController.js", "name": "ProjectController.js", "qualifier": "FIL", "path": "src/controller/ProjectController.js", "language": "js", "measures": [{"metric": "complexity", "value": "34"}, {"metric": "functions", "value": "32"}, {"metric": "ncloc", "value": "113"}, {"metric": "coverage", "value": "95.4", "bestValue": false}, {"metric": "security_rating", "value": "1.0", "bestValue": true}, {"metric": "comment_lines_density", "value": "0.0", "bestValue": false}, {"metric": "files", "value": "1"}, {"metric": "duplicated_lines_density", "value": "0.0", "bestValue": true}, {"metric": "test_errors", "value": "0", "bestValue": true}, {"metric": "test_failures", "value": "0", "bestValue": true}]}, {"id": "AYhUIFXjntWG4CW0DqlO", "key": "fga-eps-mds_2023-1-PUMA-ProjectService:tests/unit/controller/ProjectController.test.js", "name": "ProjectController.test.js", "qualifier": "UTS", "path": "tests/unit/controller/ProjectController.test.js", "language": "js", "measures": [{"metric": "security_rating", "value": "1.0", "bestValue": true}, {"metric": "duplicated_lines_density", "value": "0.0", "bestValue": true}, {"metric": "test_errors", "value": "0", "bestValue": true}, {"metric": "test_failures", "value": "0", "bestValue": true}]}, {"id": "AYhUIFXjntWG4CW0Dqkb", "key": "fga-eps-mds_2023-1-PUMA-ProjectService:src/repository/projectRepository.js", "name": "projectRepository.js", "qualifier": "FIL", "path": "src/repository/projectRepository.js", "language": "js", "measures": [{"metric": "complexity", "value": "54"}, {"metric": "functions", "value": "49"}, {"metric": "ncloc", "value": "209"}, {"metric": "coverage", "value": "81.7", "bestValue": false}, {"metric": "security_rating", "value": "1.0", "bestValue": true}, {"metric": "comment_lines_density", "value": "0.5", "bestValue": false}, {"metric": "files", "value": "1"}, {"metric": "duplicated_lines_density", "value": "0.0", "bestValue": true}, {"metric": "test_errors", "value": "0", "bestValue": true}, {"metric": "test_failures", "value": "0", "bestValue": true}]}, {"id": "AYhUIFXjntWG4CW0DqlG", "key": "fga-eps-mds_2023-1-PUMA-ProjectService:tests/unit/repository/ProjectRepository.test.js", "name": "ProjectRepository.test.js", "qualifier": "UTS", "path": "tests/unit/repository/ProjectRepository.test.js", "language": "js", "measures": [{"metric": "security_rating", "value": "1.0", "bestValue": true}, {"metric": "duplicated_lines_density", "value": "0.0", "bestValue": true}, {"metric": "test_errors", "value": "0", "bestValue": true}, {"metric": "test_failures", "value": "0", "bestValue": true}]}, {"id": "AYhjjaD1HdRBtAUiJyEh", "key": "fga-eps-mds_2023-1-PUMA-ProjectService:src/controller/PumaInfoController.js", "name": "PumaInfoController.js", "qualifier": "FIL", "path": "src/controller/PumaInfoController.js", "language": "js", "measures": [{"metric": "complexity", "value": "4"}, {"metric": "functions", "value": "4"}, {"metric": "ncloc", "value": "22"}, {"metric": "coverage", "value": "0.0", "bestValue": false}, {"metric": "security_rating", "value": "1.0", "bestValue": true}, {"metric": "comment_lines_density", "value": "0.0", "bestValue": false}, {"metric": "files", "value": "1"}, {"metric": "duplicated_lines_density", "value": "0.0", "bestValue": true}, {"metric": "test_errors", "value": "0", "bestValue": true}, {"metric": "test_failures", "value": "0", "bestValue": true}]}, {"id": "AYhjjaD1HdRBtAUiJyEg", "key": "fga-eps-mds_2023-1-PUMA-ProjectService:src/repository/pumaInfoRepository.js", "name": "pumaInfoRepository.js", "qualifier": "FIL", "path": "src/repository/pumaInfoRepository.js", "language": "js", "measures": [{"metric": "functions", "value": "15"}, {"metric": "security_rating", "value": "1.0", "bestValue": true}, {"metric": "files", "value": "1"}, {"metric": "complexity", "value": "28"}, {"metric": "ncloc", "value": "191"}, {"metric": "coverage", "value": "0.0", "bestValue": false}, {"metric": "comment_lines_density", "value": "1.5", "bestValue": false}, {"metric": "duplicated_lines_density", "value": "0.0", "bestValue": true}, {"metric": "test_errors", "value": "0", "bestValue": true}, {"metric": "test_failures", "value": "0", "bestValue": true}]}, {"id": "AYhUIFXjntWG4CW0Dqkd", "key": "fga-eps-mds_2023-1-PUMA-ProjectService:src/repository", "name": "repository", "qualifier": "DIR", "path": "src/repository", "measures": [{"metric": "duplicated_lines_density", "value": "0.0", "bestValue": true}, {"metric": "functions", "value": "250"}, {"metric": "security_rating", "value": "1.0", "bestValue": true}, {"metric": "files", "value": "10"}, {"metric": "complexity", "value": "273"}, {"metric": "ncloc", "value": "1006"}, {"metric": "coverage", "value": "69.8", "bestValue": false}, {"metric": "comment_lines_density", "value": "0.4", "bestValue": false}]}, {"id": "AYhUIFXjntWG4CW0DqlN", "key": "fga-eps-mds_2023-1-PUMA-ProjectService:tests/unit/repository", "name": "repository", "qualifier": "DIR", "path": "tests/unit/repository", "measures": [{"metric": "security_rating", "value": "1.0", "bestValue": true}]}, {"id": "AYhUIFXjntWG4CW0DqkX", "key": "fga-eps-mds_2023-1-PUMA-ProjectService:src/repository/semesterRepository.js", "name": "semesterRepository.js", "qualifier": "FIL", "path": "src/repository/semesterRepository.js", "language": "js", "measures": [{"metric": "complexity", "value": "4"}, {"metric": "functions", "value": "4"}, {"metric": "ncloc", "value": "13"}, {"metric": "coverage", "value": "100.0", "bestValue": true}, {"metric": "security_rating", "value": "1.0", "bestValue": true}, {"metric": "comment_lines_density", "value": "0.0", "bestValue": false}, {"metric": "files", "value": "1"}, {"metric": "duplicated_lines_density", "value": "0.0", "bestValue": true}, {"metric": "test_errors", "value": "0", "bestValue": true}, {"metric": "test_failures", "value": "0", "bestValue": true}]}, {"id": "AYhUIFXjntWG4CW0DqlL", "key": "fga-eps-mds_2023-1-PUMA-ProjectService:tests/unit/repository/SemesterRepository.test.js", "name": "SemesterRepository.test.js", "qualifier": "UTS", "path": "tests/unit/repository/SemesterRepository.test.js", "language": "js", "measures": [{"metric": "security_rating", "value": "1.0", "bestValue": true}, {"metric": "duplicated_lines_density", "value": "0.0", "bestValue": true}, {"metric": "test_errors", "value": "0", "bestValue": true}, {"metric": "test_failures", "value": "0", "bestValue": true}]}, {"id": "AYhUIFXjntWG4CW0Dqk6", "key": "fga-eps-mds_2023-1-PUMA-ProjectService:src/service", "name": "service", "qualifier": "DIR", "path": "src/service", "measures": [{"metric": "duplicated_lines_density", "value": "0.0", "bestValue": true}, {"metric": "functions", "value": "0"}, {"metric": "security_rating", "value": "1.0", "bestValue": true}, {"metric": "files", "value": "1"}, {"metric": "complexity", "value": "0"}, {"metric": "ncloc", "value": "0"}, {"metric": "comment_lines_density", "value": "100.0", "bestValue": true}]}, {"id": "AYhUIFXjntWG4CW0DqlE", "key": "fga-eps-mds_2023-1-PUMA-ProjectService:src", "name": "src", "qualifier": "DIR", "path": "src", "measures": [{"metric": "duplicated_lines_density", "value": "0.0", "bestValue": true}, {"metric": "functions", "value": "353"}, {"metric": "security_rating", "value": "1.0", "bestValue": true}, {"metric": "files", "value": "20"}, {"metric": "complexity", "value": "385"}, {"metric": "ncloc", "value": "1553"}, {"metric": "coverage", "value": "72.8", "bestValue": false}, {"metric": "comment_lines_density", "value": "2.6", "bestValue": false}]}, {"id": "AYhUIFXjntWG4CW0Dqkc", "key": "fga-eps-mds_2023-1-PUMA-ProjectService:src/repository/subareaRepository.js", "name": "subareaRepository.js", "qualifier": "FIL", "path": "src/repository/subareaRepository.js", "language": "js", "measures": [{"metric": "complexity", "value": "20"}, {"metric": "functions", "value": "20"}, {"metric": "ncloc", "value": "57"}, {"metric": "coverage", "value": "96.6", "bestValue": false}, {"metric": "security_rating", "value": "1.0", "bestValue": true}, {"metric": "comment_lines_density", "value": "0.0", "bestValue": false}, {"metric": "files", "value": "1"}, {"metric": "duplicated_lines_density", "value": "0.0", "bestValue": true}, {"metric": "test_errors", "value": "0", "bestValue": true}, {"metric": "test_failures", "value": "0", "bestValue": true}]}, {"id": "AYhUIFXjntWG4CW0DqlI", "key": "fga-eps-mds_2023-1-PUMA-ProjectService:tests/unit/repository/SubareaRepository.test.js", "name": "SubareaRepository.test.js", "qualifier": "UTS", "path": "tests/unit/repository/SubareaRepository.test.js", "language": "js", "measures": [{"metric": "security_rating", "value": "1.0", "bestValue": true}, {"metric": "duplicated_lines_density", "value": "0.0", "bestValue": true}, {"metric": "test_errors", "value": "0", "bestValue": true}, {"metric": "test_failures", "value": "0", "bestValue": true}]}, {"id": "AYhUIFXjntWG4CW0Dqk-", "key": "fga-eps-mds_2023-1-PUMA-ProjectService:src/controller/SubjectController.js", "name": "SubjectController.js", "qualifier": "FIL", "path": "src/controller/SubjectController.js", "language": "js", "measures": [{"metric": "complexity", "value": "29"}, {"metric": "functions", "value": "24"}, {"metric": "ncloc", "value": "169"}, {"metric": "coverage", "value": "88.3", "bestValue": false}, {"metric": "security_rating", "value": "1.0", "bestValue": true}, {"metric": "comment_lines_density", "value": "0.0", "bestValue": false}, {"metric": "files", "value": "1"}, {"metric": "duplicated_lines_density", "value": "0.0", "bestValue": true}, {"metric": "test_errors", "value": "0", "bestValue": true}, {"metric": "test_failures", "value": "0", "bestValue": true}]}, {"id": "AYhUIFXjntWG4CW0DqlQ", "key": "fga-eps-mds_2023-1-PUMA-ProjectService:tests/unit/controller/SubjectController.test.js", "name": "SubjectController.test.js", "qualifier": "UTS", "path": "tests/unit/controller/SubjectController.test.js", "language": "js", "measures": [{"metric": "security_rating", "value": "1.0", "bestValue": true}, {"metric": "duplicated_lines_density", "value": "0.0", "bestValue": true}, {"metric": "test_errors", "value": "0", "bestValue": true}, {"metric": "test_failures", "value": "0", "bestValue": true}]}, {"id": "AYhUIFXjntWG4CW0DqkV", "key": "fga-eps-mds_2023-1-PUMA-ProjectService:src/repository/subjectRepository.js", "name": "subjectRepository.js", "qualifier": "FIL", "path": "src/repository/subjectRepository.js", "language": "js", "measures": [{"metric": "complexity", "value": "20"}, {"metric": "functions", "value": "20"}, {"metric": "ncloc", "value": "66"}, {"metric": "coverage", "value": "100.0", "bestValue": true}, {"metric": "security_rating", "value": "1.0", "bestValue": true}, {"metric": "comment_lines_density", "value": "0.0", "bestValue": false}, {"metric": "files", "value": "1"}, {"metric": "duplicated_lines_density", "value": "0.0", "bestValue": true}, {"metric": "test_errors", "value": "0", "bestValue": true}, {"metric": "test_failures", "value": "0", "bestValue": true}]}, {"id": "AYhUIFXjntWG4CW0DqlH", "key": "fga-eps-mds_2023-1-PUMA-ProjectService:tests/unit/repository/SubjectRepository.test.js", "name": "SubjectRepository.test.js", "qualifier": "UTS", "path": "tests/unit/repository/SubjectRepository.test.js", "language": "js", "measures": [{"metric": "security_rating", "value": "1.0", "bestValue": true}, {"metric": "duplicated_lines_density", "value": "0.0", "bestValue": true}, {"metric": "test_errors", "value": "0", "bestValue": true}, {"metric": "test_failures", "value": "0", "bestValue": true}]}, {"id": "AYhUIFXjntWG4CW0DqlT", "key": "fga-eps-mds_2023-1-PUMA-ProjectService:tests/unit", "name": "tests/unit", "qualifier": "DIR", "path": "tests/unit", "measures": [{"metric": "security_rating", "value": "1.0", "bestValue": true}]}, {"id": "AYhUIFXjntWG4CW0Dqk4", "key": "fga-eps-mds_2023-1-PUMA-ProjectService:src/utils", "name": "utils", "qualifier": "DIR", "path": "src/utils", "measures": [{"metric": "duplicated_lines_density", "value": "0.0", "bestValue": true}, {"metric": "functions", "value": "1"}, {"metric": "security_rating", "value": "1.0", "bestValue": true}, {"metric": "files", "value": "3"}, {"metric": "complexity", "value": "3"}, {"metric": "ncloc", "value": "63"}, {"metric": "coverage", "value": "50.0", "bestValue": false}, {"metric": "comment_lines_density", "value": "23.2", "bestValue": false}]}]}